{
  "config_id": "blend-weight-08",
  "config_hash": "85afb8a8856bca389fdd9d8db219aae9182b24d1e0b5acc41ad5f085e8221057",
  "config_hash_note": "config_hash was computed with the pre-2026-06 broken canonicalisation (all configs hashed identically; see COR-01). Not valid for promotion checks - re-run the backtest to regenerate.",
  "ran_at": "2026-04-26T03:47:15.967Z",
  "data_through": "2026-04-25",
  "scope": {
    "seasons": [
      2021,
      2022,
      2023,
      2024,
      2025
    ]
  },
  "overall": {
    "matches": 1062,
    "tips": 692,
    "tip_pct": 0.6577946768060836,
    "mae_margin": 27.81425039594312,
    "rmse_margin": 35.690738763311415,
    "log_loss_bits": 0.8818615966563728,
    "brier": 0.21162649279705453
  },
  "by_season": {
    "2021": {
      "matches": 207,
      "tips": 131,
      "tip_pct": 0.6421568627450981,
      "mae_margin": 27.567076351127486,
      "rmse_margin": 35.183707657968874,
      "log_loss_bits": 0.9194741845020059,
      "brier": 0.22270317032745476
    },
    "2022": {
      "matches": 207,
      "tips": 142,
      "tip_pct": 0.6893203883495146,
      "mae_margin": 26.711522282883763,
      "rmse_margin": 33.53822052231453,
      "log_loss_bits": 0.8593547418783529,
      "brier": 0.20420016798952081
    },
    "2023": {
      "matches": 216,
      "tips": 138,
      "tip_pct": 0.6448598130841121,
      "mae_margin": 27.956206928219654,
      "rmse_margin": 36.71976036899571,
      "log_loss_bits": 0.9031416691237661,
      "brier": 0.2186444210413153
    },
    "2024": {
      "matches": 216,
      "tips": 137,
      "tip_pct": 0.6431924882629108,
      "mae_margin": 28.062281545158793,
      "rmse_margin": 35.99969881825445,
      "log_loss_bits": 0.8999377036599426,
      "brier": 0.21767202047668288
    },
    "2025": {
      "matches": 216,
      "tips": 144,
      "tip_pct": 0.6697674418604651,
      "mae_margin": 28.717918949081028,
      "rmse_margin": 36.802353063189706,
      "log_loss_bits": 0.8280290896622806,
      "brier": 0.19506478218041898
    }
  },
  "calibration": [
    {
      "bucket": "50-60%",
      "predicted": 0.5493585208999433,
      "actual": 0.5439672801635992,
      "n": 489
    },
    {
      "bucket": "60-70%",
      "predicted": 0.6449683063337007,
      "actual": 0.6724137931034483,
      "n": 348
    },
    {
      "bucket": "70-80%",
      "predicted": 0.741687686323069,
      "actual": 0.8478260869565217,
      "n": 184
    },
    {
      "bucket": "80-90%",
      "predicted": 0.8342537861121517,
      "actual": 0.8780487804878049,
      "n": 41
    }
  ],
  "matches": []
}
